anakin_language_server-1.23.dist-info/licenses/LICENSE
anakinls/__init__.py
anakinls/__main__.py
anakinls/server.py
anakinls/version.py
anakin_language_server-1.23.dist-info/METADATA
anakin_language_server-1.23.dist-info/WHEEL
anakin_language_server-1.23.dist-info/entry_points.txt
anakin_language_server-1.23.dist-info/top_level.txt
anakin_language_server-1.23.dist-info/RECORD
