Metadata-Version: 2.4
Name: anakin-language-server
Version: 1.23
Summary: Yet another Jedi Python language server
Author-email: Andrii Kolomoiets <andreyk.mad@gmail.com>
License:                     GNU GENERAL PUBLIC LICENSE
Project-URL: Homepage, https://github.com/muffinmad/anakin-language-server
Project-URL: Bug Reports, https://github.com/muffinmad/anakin-language-server/issues
Project-URL: Source, https://github.com/muffinmad/anakin-language-server
Classifier: Development Status :: 5 - Production/Stable
Classifier: Intended Audience :: Developers
Classifier: License :: OSI Approved :: GNU General Public License v3 (GPLv3)
Classifier: Operating System :: OS Independent
Classifier: Programming Language :: Python :: 3
Classifier: Topic :: Text Editors :: Integrated Development Environments (IDE)
Requires-Python: >=3.7.16
License-File: LICENSE
Requires-Dist: jedi>=0.19.0
Requires-Dist: pygls<1.4,>=1.3
Requires-Dist: pyflakes~=2.2
Requires-Dist: pycodestyle~=2.5
Requires-Dist: yapf~=0.30
Dynamic: license-file
